pyfunctionbases/__init__.py
pyfunctionbases/expansions.py
pyfunctionbases/function_definitions.py
pyfunctionbases-1.6.dist-info/METADATA
pyfunctionbases-1.6.dist-info/WHEEL
pyfunctionbases-1.6.dist-info/top_level.txt
pyfunctionbases-1.6.dist-info/RECORD
