Metadata-Version: 2.1
Name: pyfunctionbases
Version: 1.6
Summary: A Python module to compute multidimensional arrays of evaluated functions.
Home-page: https://github.com/NiMlr/PyFunctionBases
Author: Nils Mueller
Author-email: nils.mueller@ini.rub.de
License: MIT
Platform: UNKNOWN
